tests/test_import_dependencies.py
tests/test_import_verma_net_radiation.py
tests/test_verify.py
verma_net_radiation/ECOv002-cal-val-verma-net-radiation-inputs.csv
verma_net_radiation/ECOv002-cal-val-verma-net-radiation-outputs.csv
verma_net_radiation/ECOv002_calval_verma_net_radiation_inputs.py
verma_net_radiation/__init__.py
verma_net_radiation/brutsaert_atmospheric_emissivity.py
verma_net_radiation/constants.py
verma_net_radiation/daylight_Rn_integration_verma.py
verma_net_radiation/exceptions.py
verma_net_radiation/incoming_longwave_radiation.py
verma_net_radiation/model.py
verma_net_radiation/outgoing_longwave_radiation.py
verma_net_radiation/verify.py
verma_net_radiation/verma_net_radiation.py
verma_net_radiation/verma_net_radiation_table.py
verma_net_radiation/version.py
verma_net_radiation-1.11.0.dist-info/licenses/LICENSE
verma_net_radiation-1.11.0.dist-info/METADATA
verma_net_radiation-1.11.0.dist-info/WHEEL
verma_net_radiation-1.11.0.dist-info/top_level.txt
verma_net_radiation-1.11.0.dist-info/RECORD
