Metadata-Version: 2.4
Name: verma-net-radiation
Version: 1.11.0
Summary: Net Radiation and Daily Upscaling Remote Sensing in Python
Author-email: Gregory Halverson <gregory.h.halverson@jpl.nasa.gov>
Project-URL: Homepage, https://github.com/JPL-Evapotranspiration-Algorithms/verma-net-radiation
Classifier: Programming Language :: Python :: 3
Classifier: Operating System :: OS Independent
Requires-Python: >=3.10
License-File: LICENSE
Requires-Dist: check-distribution
Requires-Dist: ECOv002-calval-tables>=1.4.0
Requires-Dist: ECOv002-CMR>=1.1.0
Requires-Dist: ECOv002-granules
Requires-Dist: GEOS5FP>=1.2.1
Requires-Dist: monte-carlo-sensitivity
Requires-Dist: numpy
Requires-Dist: pytictoc
Requires-Dist: rasters
Requires-Dist: seaborn
Requires-Dist: solar-apparent-time>=1.5.3
Requires-Dist: sun-angles>=1.2.0
Provides-Extra: dev
Requires-Dist: build; extra == "dev"
Requires-Dist: pytest>=6.0; extra == "dev"
Requires-Dist: pytest-cov; extra == "dev"
Requires-Dist: jupyter; extra == "dev"
Requires-Dist: pytest; extra == "dev"
Requires-Dist: twine; extra == "dev"
Dynamic: license-file
